sa003package/__init__.py
sa003package/kangroll_basic_fn001_mln.py
sa003package/kangroll_basic_fn001_mln_release.py
sa003package/pytransform/__init__.py
sa003package/pytransform/_pytransform.dylib
site-pacakge-link/__init__.py
site-pacakge-link/kangroll_basic_fn001_mln.py
site-pacakge-link/kangroll_basic_fn001_mln_release.py
site-pacakge-link/pytransform/__init__.py
standalone003gntmcallmln-0.0.15.dist-info/LICENSE
standalone003gntmcallmln-0.0.15.dist-info/METADATA
standalone003gntmcallmln-0.0.15.dist-info/WHEEL
standalone003gntmcallmln-0.0.15.dist-info/top_level.txt
standalone003gntmcallmln-0.0.15.dist-info/RECORD
