Metadata-Version: 2.1
Name: standalone003gntmcallmln
Version: 0.0.15
Summary: 一个 Python 混淆工具包
Home-page: https://github.com/yourusername/standalone001pyarmor
Author: xiaowen
Author-email: xiaowenseekjob@gmail.com
Classifier: Programming Language :: Python :: 3
Classifier: License :: OSI Approved :: MIT License
Classifier: Operating System :: OS Independent
License-File: LICENSE
